{"@t":"2022-02-10T07:29:41.9361490Z","@mt":"{StartMessage} [Timing {TimingId}]","StartMessage":"Booting Umbraco 8.17.2.","TimingId":"0eb5cf8","SourceContext":"Umbraco.Core.Runtime.CoreRuntime","ProcessId":22260,"ProcessName":"iisexpress","ThreadId":1,"AppDomainId":2,"AppDomainAppId":"LMW3SVC2ROOT","MachineName":"AAR00112","Log4NetLevel":"INFO ","HttpRequestNumber":1,"HttpRequestId":"df601410-cac7-477f-9791-8cbb259d81c1"}
{"@t":"2022-02-10T07:29:41.9721503Z","@mt":"Booting site '{HostingSiteName}', app '{HostingApplicationID}', path '{HostingPhysicalPath}', server '{MachineName}'.","HostingSiteName":"Flight2Orbit","HostingApplicationID":"/LM/W3SVC/2/ROOT","HostingPhysicalPath":"C:\\Users\\Elias.Geirdal.EMEA\\git\\FlightToOrbit\\BE\\Flight2Orbit\\","MachineName":"AAR00112","SourceContext":"Umbraco.Core.Runtime.CoreRuntime","ProcessId":22260,"ProcessName":"iisexpress","ThreadId":1,"AppDomainId":2,"AppDomainAppId":"LMW3SVC2ROOT","Log4NetLevel":"INFO ","HttpRequestNumber":1,"HttpRequestId":"df601410-cac7-477f-9791-8cbb259d81c1"}
{"@t":"2022-02-10T07:29:42.2101479Z","@mt":"Acquiring.","SourceContext":"Umbraco.Core.Runtime.MainDom","ProcessId":22260,"ProcessName":"iisexpress","ThreadId":1,"AppDomainId":2,"AppDomainAppId":"LMW3SVC2ROOT","MachineName":"AAR00112","Log4NetLevel":"INFO ","HttpRequestNumber":1,"HttpRequestId":"df601410-cac7-477f-9791-8cbb259d81c1"}
{"@t":"2022-02-10T07:29:42.2131487Z","@mt":"Acquired.","SourceContext":"Umbraco.Core.Runtime.MainDom","ProcessId":22260,"ProcessName":"iisexpress","ThreadId":1,"AppDomainId":2,"AppDomainAppId":"LMW3SVC2ROOT","MachineName":"AAR00112","Log4NetLevel":"INFO ","HttpRequestNumber":1,"HttpRequestId":"df601410-cac7-477f-9791-8cbb259d81c1"}
{"@t":"2022-02-10T07:29:43.7101466Z","@mt":"{StartMessage} [Timing {TimingId}]","StartMessage":"Resolving composer types.","TimingId":"406d6f1","SourceContext":"Umbraco.Core.Runtime.CoreRuntime","ProcessId":22260,"ProcessName":"iisexpress","ThreadId":1,"AppDomainId":2,"AppDomainAppId":"LMW3SVC2ROOT","MachineName":"AAR00112","Log4NetLevel":"INFO ","HttpRequestNumber":1,"HttpRequestId":"df601410-cac7-477f-9791-8cbb259d81c1"}
{"@t":"2022-02-10T07:29:43.9171440Z","@mt":"{EndMessage} ({Duration}ms) [Timing {TimingId}]","EndMessage":"Resolved.","Duration":206,"TimingId":"406d6f1","SourceContext":"Umbraco.Core.Runtime.CoreRuntime","ProcessId":22260,"ProcessName":"iisexpress","ThreadId":1,"AppDomainId":2,"AppDomainAppId":"LMW3SVC2ROOT","MachineName":"AAR00112","Log4NetLevel":"INFO ","HttpRequestNumber":1,"HttpRequestId":"df601410-cac7-477f-9791-8cbb259d81c1"}
{"@t":"2022-02-10T07:29:45.0541484Z","@mt":"Profiler is VoidProfiler, not profiling (must run debug mode to profile).","SourceContext":"Umbraco.Web.Logging.WebProfilerComponent","ProcessId":22260,"ProcessName":"iisexpress","ThreadId":1,"AppDomainId":2,"AppDomainAppId":"LMW3SVC2ROOT","MachineName":"AAR00112","Log4NetLevel":"INFO ","HttpRequestNumber":1,"HttpRequestId":"df601410-cac7-477f-9791-8cbb259d81c1"}
{"@t":"2022-02-10T07:29:45.3761473Z","@mt":"Initializing Umbraco internal event handlers for cache refreshing.","SourceContext":"Umbraco.Web.Cache.DistributedCacheBinderComponent","ProcessId":22260,"ProcessName":"iisexpress","ThreadId":1,"AppDomainId":2,"AppDomainAppId":"LMW3SVC2ROOT","MachineName":"AAR00112","Log4NetLevel":"INFO ","HttpRequestNumber":1,"HttpRequestId":"df601410-cac7-477f-9791-8cbb259d81c1"}
{"@t":"2022-02-10T07:29:45.5271446Z","@mt":"Adding examine event handlers for {RegisteredIndexers} index providers.","RegisteredIndexers":3,"SourceContext":"Umbraco.Web.Search.ExamineComponent","ProcessId":22260,"ProcessName":"iisexpress","ThreadId":1,"AppDomainId":2,"AppDomainAppId":"LMW3SVC2ROOT","MachineName":"AAR00112","Log4NetLevel":"INFO ","HttpRequestNumber":1,"HttpRequestId":"df601410-cac7-477f-9791-8cbb259d81c1"}
{"@t":"2022-02-10T07:29:45.6411489Z","@mt":"{EndMessage} ({Duration}ms) [Timing {TimingId}]","EndMessage":"Booted.","Duration":3723,"TimingId":"0eb5cf8","SourceContext":"Umbraco.Core.Runtime.CoreRuntime","ProcessId":22260,"ProcessName":"iisexpress","ThreadId":1,"AppDomainId":2,"AppDomainAppId":"LMW3SVC2ROOT","MachineName":"AAR00112","Log4NetLevel":"INFO ","HttpRequestNumber":1,"HttpRequestId":"df601410-cac7-477f-9791-8cbb259d81c1"}
{"@t":"2022-02-10T07:29:46.4321611Z","@mt":"New url {Url} detected, re-discovering application url.","Url":"http://localhost:54252/umbraco","SourceContext":"Umbraco.Core.Sync.ApplicationUrlHelper","ProcessId":22260,"ProcessName":"iisexpress","ThreadId":9,"AppDomainId":2,"AppDomainAppId":"LMW3SVC2ROOT","MachineName":"AAR00112","Log4NetLevel":"INFO ","HttpRequestNumber":2,"HttpRequestId":"d05a7bdc-27f7-4af4-8211-87d322a29af9"}
{"@t":"2022-02-10T07:29:46.4371448Z","@mt":"ApplicationUrl: {UmbracoAppUrl} (UmbracoModule request)","UmbracoAppUrl":"http://localhost:54252/umbraco","SourceContext":"Umbraco.Core.Sync.ApplicationUrlHelper","ProcessId":22260,"ProcessName":"iisexpress","ThreadId":9,"AppDomainId":2,"AppDomainAppId":"LMW3SVC2ROOT","MachineName":"AAR00112","Log4NetLevel":"INFO ","HttpRequestNumber":2,"HttpRequestId":"d05a7bdc-27f7-4af4-8211-87d322a29af9"}
{"@t":"2022-02-10T07:29:47.6521418Z","@mt":"Registered with MainDom, localContentDbExists? {LocalContentDbExists}, localMediaDbExists? {LocalMediaDbExists}","LocalContentDbExists":true,"LocalMediaDbExists":true,"SourceContext":"Umbraco.Web.PublishedCache.NuCache.PublishedSnapshotService","ProcessId":22260,"ProcessName":"iisexpress","ThreadId":9,"AppDomainId":2,"AppDomainAppId":"LMW3SVC2ROOT","MachineName":"AAR00112","Log4NetLevel":"INFO ","HttpRequestNumber":2,"HttpRequestId":"d05a7bdc-27f7-4af4-8211-87d322a29af9"}
{"@t":"2022-02-10T07:29:47.6521418Z","@mt":"Creating the content store, localContentDbExists? {LocalContentDbExists}","LocalContentDbExists":true,"SourceContext":"Umbraco.Web.PublishedCache.NuCache.PublishedSnapshotService","ProcessId":22260,"ProcessName":"iisexpress","ThreadId":9,"AppDomainId":2,"AppDomainAppId":"LMW3SVC2ROOT","MachineName":"AAR00112","Log4NetLevel":"INFO ","HttpRequestNumber":2,"HttpRequestId":"d05a7bdc-27f7-4af4-8211-87d322a29af9"}
{"@t":"2022-02-10T07:29:47.6561457Z","@mt":"Creating the media store, localMediaDbExists? {LocalMediaDbExists}","LocalMediaDbExists":true,"SourceContext":"Umbraco.Web.PublishedCache.NuCache.PublishedSnapshotService","ProcessId":22260,"ProcessName":"iisexpress","ThreadId":9,"AppDomainId":2,"AppDomainAppId":"LMW3SVC2ROOT","MachineName":"AAR00112","Log4NetLevel":"INFO ","HttpRequestNumber":2,"HttpRequestId":"d05a7bdc-27f7-4af4-8211-87d322a29af9"}
{"@t":"2022-02-10T07:29:47.6941457Z","@mt":"No last synced Id found, this generally means this is a new server/install. The server will build its caches and indexes, and then adjust its last synced Id to the latest found in the database and maintain cache updates based on that Id.","@l":"Warning","SourceContext":"Umbraco.Core.Sync.DatabaseServerMessenger","ProcessId":22260,"ProcessName":"iisexpress","ThreadId":9,"AppDomainId":2,"AppDomainAppId":"LMW3SVC2ROOT","MachineName":"AAR00112","Log4NetLevel":"WARN ","HttpRequestNumber":2,"HttpRequestId":"d05a7bdc-27f7-4af4-8211-87d322a29af9"}
{"@t":"2022-02-10T07:29:48.8951460Z","@mt":"{StartMessage} [Timing {TimingId}]","StartMessage":"Loading content from database","TimingId":"150bd7c","SourceContext":"Umbraco.Web.PublishedCache.NuCache.PublishedSnapshotService","ProcessId":22260,"ProcessName":"iisexpress","ThreadId":9,"AppDomainId":2,"AppDomainAppId":"LMW3SVC2ROOT","MachineName":"AAR00112","Log4NetLevel":"INFO ","HttpRequestNumber":2,"HttpRequestId":"d05a7bdc-27f7-4af4-8211-87d322a29af9"}
{"@t":"2022-02-10T07:29:49.6881445Z","@mt":"{EndMessage} ({Duration}ms) [Timing {TimingId}]","EndMessage":"Completed.","Duration":793,"TimingId":"150bd7c","SourceContext":"Umbraco.Web.PublishedCache.NuCache.PublishedSnapshotService","ProcessId":22260,"ProcessName":"iisexpress","ThreadId":9,"AppDomainId":2,"AppDomainAppId":"LMW3SVC2ROOT","MachineName":"AAR00112","Log4NetLevel":"INFO ","HttpRequestNumber":2,"HttpRequestId":"d05a7bdc-27f7-4af4-8211-87d322a29af9"}
{"@t":"2022-02-10T07:29:49.7681464Z","@mt":"{StartMessage} [Timing {TimingId}]","StartMessage":"Loading media from database","TimingId":"858e381","SourceContext":"Umbraco.Web.PublishedCache.NuCache.PublishedSnapshotService","ProcessId":22260,"ProcessName":"iisexpress","ThreadId":9,"AppDomainId":2,"AppDomainAppId":"LMW3SVC2ROOT","MachineName":"AAR00112","Log4NetLevel":"INFO ","HttpRequestNumber":2,"HttpRequestId":"d05a7bdc-27f7-4af4-8211-87d322a29af9"}
{"@t":"2022-02-10T07:29:49.8581436Z","@mt":"{EndMessage} ({Duration}ms) [Timing {TimingId}]","EndMessage":"Completed.","Duration":90,"TimingId":"858e381","SourceContext":"Umbraco.Web.PublishedCache.NuCache.PublishedSnapshotService","ProcessId":22260,"ProcessName":"iisexpress","ThreadId":9,"AppDomainId":2,"AppDomainAppId":"LMW3SVC2ROOT","MachineName":"AAR00112","Log4NetLevel":"INFO ","HttpRequestNumber":2,"HttpRequestId":"d05a7bdc-27f7-4af4-8211-87d322a29af9"}
{"@t":"2022-02-10T07:29:50.2771432Z","@mt":"Starting initialize async background thread.","SourceContext":"Umbraco.Web.Search.BackgroundIndexRebuilder","ProcessId":22260,"ProcessName":"iisexpress","ThreadId":9,"AppDomainId":2,"AppDomainAppId":"LMW3SVC2ROOT","MachineName":"AAR00112","Log4NetLevel":"INFO ","HttpRequestNumber":2,"HttpRequestId":"d05a7bdc-27f7-4af4-8211-87d322a29af9"}
{"@t":"2022-02-10T07:30:06.7621374Z","@mt":"[{EventType}] Event Id: {EventId}, State: {State}","EventType":"Information","EventId":0,"State":"Login attempt succeeded for username Elias.Geirdal@akqa.com from IP address ::1","SourceContext":"Umbraco.Core.Logging.OwinLogger","ProcessId":22260,"ProcessName":"iisexpress","ThreadId":12,"AppDomainId":2,"AppDomainAppId":"LMW3SVC2ROOT","MachineName":"AAR00112","Log4NetLevel":"INFO ","HttpRequestNumber":3,"HttpRequestId":"ddf3c575-360a-4fdc-8d5b-edbc4f9d6a5b"}
{"@t":"2022-02-10T07:30:06.7631362Z","@mt":"[{EventType}] Event Id: {EventId}, State: {State}","EventType":"Information","EventId":0,"State":"User: Elias.Geirdal@akqa.com logged in from IP address ::1","SourceContext":"Umbraco.Core.Logging.OwinLogger","ProcessId":22260,"ProcessName":"iisexpress","ThreadId":12,"AppDomainId":2,"AppDomainAppId":"LMW3SVC2ROOT","MachineName":"AAR00112","Log4NetLevel":"INFO ","HttpRequestNumber":3,"HttpRequestId":"ddf3c575-360a-4fdc-8d5b-edbc4f9d6a5b"}
{"@t":"2022-02-10T07:32:50.4928120Z","@mt":"Scheduled health check results:","SourceContext":"Umbraco.Web.HealthCheck.HealthCheckResults","ProcessId":22260,"ProcessName":"iisexpress","ThreadId":41,"AppDomainId":2,"AppDomainAppId":"LMW3SVC2ROOT","MachineName":"AAR00112","Log4NetLevel":"INFO "}
{"@t":"2022-02-10T07:32:50.4928120Z","@mt":"Checks for '{HealthCheckName}' all completed successfully.","HealthCheckName":"Folder & File Permissions","SourceContext":"Umbraco.Web.HealthCheck.HealthCheckResults","ProcessId":22260,"ProcessName":"iisexpress","ThreadId":41,"AppDomainId":2,"AppDomainAppId":"LMW3SVC2ROOT","MachineName":"AAR00112","Log4NetLevel":"INFO "}
{"@t":"2022-02-10T07:32:50.4928120Z","@mt":"Result for {HealthCheckName}: {HealthCheckResult}, Message: '{HealthCheckMessage}'","HealthCheckName":"Folder & File Permissions","HealthCheckResult":"Success","HealthCheckMessage":"All folders have the correct permissions set.","SourceContext":"Umbraco.Web.HealthCheck.HealthCheckResults","ProcessId":22260,"ProcessName":"iisexpress","ThreadId":41,"AppDomainId":2,"AppDomainAppId":"LMW3SVC2ROOT","MachineName":"AAR00112","Log4NetLevel":"INFO "}
{"@t":"2022-02-10T07:32:50.4928120Z","@mt":"Result for {HealthCheckName}: {HealthCheckResult}, Message: '{HealthCheckMessage}'","HealthCheckName":"Folder & File Permissions","HealthCheckResult":"Success","HealthCheckMessage":"All files have the correct permissions set.","SourceContext":"Umbraco.Web.HealthCheck.HealthCheckResults","ProcessId":22260,"ProcessName":"iisexpress","ThreadId":41,"AppDomainId":2,"AppDomainAppId":"LMW3SVC2ROOT","MachineName":"AAR00112","Log4NetLevel":"INFO "}
{"@t":"2022-02-10T07:32:50.4938442Z","@mt":"Checks for '{HealthCheckName}' completed with errors.","@l":"Warning","HealthCheckName":"SMTP Settings","SourceContext":"Umbraco.Web.HealthCheck.HealthCheckResults","ProcessId":22260,"ProcessName":"iisexpress","ThreadId":41,"AppDomainId":2,"AppDomainAppId":"LMW3SVC2ROOT","MachineName":"AAR00112","Log4NetLevel":"WARN "}
{"@t":"2022-02-10T07:32:50.4938442Z","@mt":"Result for {HealthCheckName}: {HealthCheckResult}, Message: '{HealthCheckMessage}'","HealthCheckName":"SMTP Settings","HealthCheckResult":"Error","HealthCheckMessage":"In the Web.config file system.net/mailsettings section, the host is not configured.","SourceContext":"Umbraco.Web.HealthCheck.HealthCheckResults","ProcessId":22260,"ProcessName":"iisexpress","ThreadId":41,"AppDomainId":2,"AppDomainAppId":"LMW3SVC2ROOT","MachineName":"AAR00112","Log4NetLevel":"INFO "}
{"@t":"2022-02-10T07:32:50.4938442Z","@mt":"Checks for '{HealthCheckName}' completed with errors.","@l":"Warning","HealthCheckName":"Cross-site scripting Protection (X-XSS-Protection header)","SourceContext":"Umbraco.Web.HealthCheck.HealthCheckResults","ProcessId":22260,"ProcessName":"iisexpress","ThreadId":41,"AppDomainId":2,"AppDomainAppId":"LMW3SVC2ROOT","MachineName":"AAR00112","Log4NetLevel":"WARN "}
{"@t":"2022-02-10T07:32:50.4938442Z","@mt":"Result for {HealthCheckName}: {HealthCheckResult}, Message: '{HealthCheckMessage}'","HealthCheckName":"Cross-site scripting Protection (X-XSS-Protection header)","HealthCheckResult":"Error","HealthCheckMessage":"The header <strong>X-XSS-Protection</strong> was not found.","SourceContext":"Umbraco.Web.HealthCheck.HealthCheckResults","ProcessId":22260,"ProcessName":"iisexpress","ThreadId":41,"AppDomainId":2,"AppDomainAppId":"LMW3SVC2ROOT","MachineName":"AAR00112","Log4NetLevel":"INFO "}
{"@t":"2022-02-10T07:32:50.4938442Z","@mt":"Checks for '{HealthCheckName}' completed with errors.","@l":"Warning","HealthCheckName":"Cookie hijacking and protocol downgrade attacks Protection (Strict-Transport-Security Header (HSTS))","SourceContext":"Umbraco.Web.HealthCheck.HealthCheckResults","ProcessId":22260,"ProcessName":"iisexpress","ThreadId":41,"AppDomainId":2,"AppDomainAppId":"LMW3SVC2ROOT","MachineName":"AAR00112","Log4NetLevel":"WARN "}
{"@t":"2022-02-10T07:32:50.4938442Z","@mt":"Result for {HealthCheckName}: {HealthCheckResult}, Message: '{HealthCheckMessage}'","HealthCheckName":"Cookie hijacking and protocol downgrade attacks Protection (Strict-Transport-Security Header (HSTS))","HealthCheckResult":"Error","HealthCheckMessage":"The header <strong>Strict-Transport-Security</strong> was not found.","SourceContext":"Umbraco.Web.HealthCheck.HealthCheckResults","ProcessId":22260,"ProcessName":"iisexpress","ThreadId":41,"AppDomainId":2,"AppDomainAppId":"LMW3SVC2ROOT","MachineName":"AAR00112","Log4NetLevel":"INFO "}
{"@t":"2022-02-10T07:32:50.4938442Z","@mt":"Checks for '{HealthCheckName}' completed with errors.","@l":"Warning","HealthCheckName":"Content/MIME Sniffing Protection","SourceContext":"Umbraco.Web.HealthCheck.HealthCheckResults","ProcessId":22260,"ProcessName":"iisexpress","ThreadId":41,"AppDomainId":2,"AppDomainAppId":"LMW3SVC2ROOT","MachineName":"AAR00112","Log4NetLevel":"WARN "}
{"@t":"2022-02-10T07:32:50.4938442Z","@mt":"Result for {HealthCheckName}: {HealthCheckResult}, Message: '{HealthCheckMessage}'","HealthCheckName":"Content/MIME Sniffing Protection","HealthCheckResult":"Error","HealthCheckMessage":"The header or meta-tag <strong>X-Content-Type-Options</strong> used to protect against MIME sniffing vulnerabilities was not found.","SourceContext":"Umbraco.Web.HealthCheck.HealthCheckResults","ProcessId":22260,"ProcessName":"iisexpress","ThreadId":41,"AppDomainId":2,"AppDomainAppId":"LMW3SVC2ROOT","MachineName":"AAR00112","Log4NetLevel":"INFO "}
{"@t":"2022-02-10T07:32:50.4938442Z","@mt":"Checks for '{HealthCheckName}' completed with errors.","@l":"Warning","HealthCheckName":"Excessive Headers","SourceContext":"Umbraco.Web.HealthCheck.HealthCheckResults","ProcessId":22260,"ProcessName":"iisexpress","ThreadId":41,"AppDomainId":2,"AppDomainAppId":"LMW3SVC2ROOT","MachineName":"AAR00112","Log4NetLevel":"WARN "}
{"@t":"2022-02-10T07:32:50.4938442Z","@mt":"Result for {HealthCheckName}: {HealthCheckResult}, Message: '{HealthCheckMessage}'","HealthCheckName":"Excessive Headers","HealthCheckResult":"Warning","HealthCheckMessage":"[httpsCheckInvalidUrl]","SourceContext":"Umbraco.Web.HealthCheck.HealthCheckResults","ProcessId":22260,"ProcessName":"iisexpress","ThreadId":41,"AppDomainId":2,"AppDomainAppId":"LMW3SVC2ROOT","MachineName":"AAR00112","Log4NetLevel":"INFO "}
{"@t":"2022-02-10T07:32:50.4938442Z","@mt":"Checks for '{HealthCheckName}' completed with errors.","@l":"Warning","HealthCheckName":"Click-Jacking Protection","SourceContext":"Umbraco.Web.HealthCheck.HealthCheckResults","ProcessId":22260,"ProcessName":"iisexpress","ThreadId":41,"AppDomainId":2,"AppDomainAppId":"LMW3SVC2ROOT","MachineName":"AAR00112","Log4NetLevel":"WARN "}
{"@t":"2022-02-10T07:32:50.4938442Z","@mt":"Result for {HealthCheckName}: {HealthCheckResult}, Message: '{HealthCheckMessage}'","HealthCheckName":"Click-Jacking Protection","HealthCheckResult":"Error","HealthCheckMessage":"The header or meta-tag <strong>X-Frame-Options</strong> used to control whether a site can be IFRAMEd by another was not found.","SourceContext":"Umbraco.Web.HealthCheck.HealthCheckResults","ProcessId":22260,"ProcessName":"iisexpress","ThreadId":41,"AppDomainId":2,"AppDomainAppId":"LMW3SVC2ROOT","MachineName":"AAR00112","Log4NetLevel":"INFO "}
{"@t":"2022-02-10T07:32:50.4938442Z","@mt":"Checks for '{HealthCheckName}' completed with errors.","@l":"Warning","HealthCheckName":"HTTPS Configuration","SourceContext":"Umbraco.Web.HealthCheck.HealthCheckResults","ProcessId":22260,"ProcessName":"iisexpress","ThreadId":41,"AppDomainId":2,"AppDomainAppId":"LMW3SVC2ROOT","MachineName":"AAR00112","Log4NetLevel":"WARN "}
{"@t":"2022-02-10T07:32:50.4938442Z","@mt":"Result for {HealthCheckName}: {HealthCheckResult}, Message: '{HealthCheckMessage}'","HealthCheckName":"HTTPS Configuration","HealthCheckResult":"Error","HealthCheckMessage":"You are currently not viewing the site using the HTTPS scheme.","SourceContext":"Umbraco.Web.HealthCheck.HealthCheckResults","ProcessId":22260,"ProcessName":"iisexpress","ThreadId":41,"AppDomainId":2,"AppDomainAppId":"LMW3SVC2ROOT","MachineName":"AAR00112","Log4NetLevel":"INFO "}
{"@t":"2022-02-10T07:32:50.4938442Z","@mt":"Result for {HealthCheckName}: {HealthCheckResult}, Message: '{HealthCheckMessage}'","HealthCheckName":"HTTPS Configuration","HealthCheckResult":"Info","HealthCheckMessage":"The appSetting 'Umbraco.Core.UseHttps' is set to 'false' in your web.config file. Once you access this site using the HTTPS scheme, that should be set to 'true'.","SourceContext":"Umbraco.Web.HealthCheck.HealthCheckResults","ProcessId":22260,"ProcessName":"iisexpress","ThreadId":41,"AppDomainId":2,"AppDomainAppId":"LMW3SVC2ROOT","MachineName":"AAR00112","Log4NetLevel":"INFO "}
{"@t":"2022-02-10T07:32:50.4938442Z","@mt":"Result for {HealthCheckName}: {HealthCheckResult}, Message: '{HealthCheckMessage}'","HealthCheckName":"HTTPS Configuration","HealthCheckResult":"Error","HealthCheckMessage":"Error pinging the URL https://localhost:54252/umbraco - 'The underlying connection was closed: An unexpected error occurred on a send.'","SourceContext":"Umbraco.Web.HealthCheck.HealthCheckResults","ProcessId":22260,"ProcessName":"iisexpress","ThreadId":41,"AppDomainId":2,"AppDomainAppId":"LMW3SVC2ROOT","MachineName":"AAR00112","Log4NetLevel":"INFO "}
{"@t":"2022-02-10T07:32:50.4938442Z","@mt":"Checks for '{HealthCheckName}' all completed successfully.","HealthCheckName":"Database data integrity check","SourceContext":"Umbraco.Web.HealthCheck.HealthCheckResults","ProcessId":22260,"ProcessName":"iisexpress","ThreadId":41,"AppDomainId":2,"AppDomainAppId":"LMW3SVC2ROOT","MachineName":"AAR00112","Log4NetLevel":"INFO "}
{"@t":"2022-02-10T07:32:50.4938442Z","@mt":"Result for {HealthCheckName}: {HealthCheckResult}, Message: '{HealthCheckMessage}'","HealthCheckName":"Database data integrity check","HealthCheckResult":"Success","HealthCheckMessage":"<p>All document paths are valid</p>\r\n","SourceContext":"Umbraco.Web.HealthCheck.HealthCheckResults","ProcessId":22260,"ProcessName":"iisexpress","ThreadId":41,"AppDomainId":2,"AppDomainAppId":"LMW3SVC2ROOT","MachineName":"AAR00112","Log4NetLevel":"INFO "}
{"@t":"2022-02-10T07:32:50.4938442Z","@mt":"Result for {HealthCheckName}: {HealthCheckResult}, Message: '{HealthCheckMessage}'","HealthCheckName":"Database data integrity check","HealthCheckResult":"Success","HealthCheckMessage":"<p>All media paths are valid</p>\r\n","SourceContext":"Umbraco.Web.HealthCheck.HealthCheckResults","ProcessId":22260,"ProcessName":"iisexpress","ThreadId":41,"AppDomainId":2,"AppDomainAppId":"LMW3SVC2ROOT","MachineName":"AAR00112","Log4NetLevel":"INFO "}
{"@t":"2022-02-10T07:32:50.4938442Z","@mt":"Checks for '{HealthCheckName}' completed with errors.","@l":"Warning","HealthCheckName":"Macro errors","SourceContext":"Umbraco.Web.HealthCheck.HealthCheckResults","ProcessId":22260,"ProcessName":"iisexpress","ThreadId":41,"AppDomainId":2,"AppDomainAppId":"LMW3SVC2ROOT","MachineName":"AAR00112","Log4NetLevel":"WARN "}
{"@t":"2022-02-10T07:32:50.4938442Z","@mt":"Result for {HealthCheckName}: {HealthCheckResult}, Message: '{HealthCheckMessage}'","HealthCheckName":"Macro errors","HealthCheckResult":"Error","HealthCheckMessage":"MacroErrors are set to 'throw' which will prevent some or all pages in your site from loading completely if there are any errors in macros. Rectifying this will set the value to 'inline'.","SourceContext":"Umbraco.Web.HealthCheck.HealthCheckResults","ProcessId":22260,"ProcessName":"iisexpress","ThreadId":41,"AppDomainId":2,"AppDomainAppId":"LMW3SVC2ROOT","MachineName":"AAR00112","Log4NetLevel":"INFO "}
{"@t":"2022-02-10T07:32:50.4938442Z","@mt":"Checks for '{HealthCheckName}' completed with errors.","@l":"Warning","HealthCheckName":"Notification Email Settings","SourceContext":"Umbraco.Web.HealthCheck.HealthCheckResults","ProcessId":22260,"ProcessName":"iisexpress","ThreadId":41,"AppDomainId":2,"AppDomainAppId":"LMW3SVC2ROOT","MachineName":"AAR00112","Log4NetLevel":"WARN "}
{"@t":"2022-02-10T07:32:50.4938442Z","@mt":"Result for {HealthCheckName}: {HealthCheckResult}, Message: '{HealthCheckMessage}'","HealthCheckName":"Notification Email Settings","HealthCheckResult":"Error","HealthCheckMessage":"Notification email is still set to the default value of <strong>your@email.here</strong>.","SourceContext":"Umbraco.Web.HealthCheck.HealthCheckResults","ProcessId":22260,"ProcessName":"iisexpress","ThreadId":41,"AppDomainId":2,"AppDomainAppId":"LMW3SVC2ROOT","MachineName":"AAR00112","Log4NetLevel":"INFO "}
{"@t":"2022-02-10T07:32:50.4938442Z","@mt":"Checks for '{HealthCheckName}' all completed successfully.","HealthCheckName":"Try Skip IIS Custom Errors","SourceContext":"Umbraco.Web.HealthCheck.HealthCheckResults","ProcessId":22260,"ProcessName":"iisexpress","ThreadId":41,"AppDomainId":2,"AppDomainAppId":"LMW3SVC2ROOT","MachineName":"AAR00112","Log4NetLevel":"INFO "}
{"@t":"2022-02-10T07:32:50.4938442Z","@mt":"Result for {HealthCheckName}: {HealthCheckResult}, Message: '{HealthCheckMessage}'","HealthCheckName":"Try Skip IIS Custom Errors","HealthCheckResult":"Success","HealthCheckMessage":"Try Skip IIS Custom Errors is set to 'true' and you're using IIS version '10.0'.","SourceContext":"Umbraco.Web.HealthCheck.HealthCheckResults","ProcessId":22260,"ProcessName":"iisexpress","ThreadId":41,"AppDomainId":2,"AppDomainAppId":"LMW3SVC2ROOT","MachineName":"AAR00112","Log4NetLevel":"INFO "}
{"@t":"2022-02-10T07:32:50.4938442Z","@mt":"Checks for '{HealthCheckName}' all completed successfully.","HealthCheckName":"Custom Errors","SourceContext":"Umbraco.Web.HealthCheck.HealthCheckResults","ProcessId":22260,"ProcessName":"iisexpress","ThreadId":41,"AppDomainId":2,"AppDomainAppId":"LMW3SVC2ROOT","MachineName":"AAR00112","Log4NetLevel":"INFO "}
{"@t":"2022-02-10T07:32:50.4938442Z","@mt":"Result for {HealthCheckName}: {HealthCheckResult}, Message: '{HealthCheckMessage}'","HealthCheckName":"Custom Errors","HealthCheckResult":"Success","HealthCheckMessage":"Custom errors are set to 'RemoteOnly'.","SourceContext":"Umbraco.Web.HealthCheck.HealthCheckResults","ProcessId":22260,"ProcessName":"iisexpress","ThreadId":41,"AppDomainId":2,"AppDomainAppId":"LMW3SVC2ROOT","MachineName":"AAR00112","Log4NetLevel":"INFO "}
{"@t":"2022-02-10T07:32:50.4938442Z","@mt":"Checks for '{HealthCheckName}' all completed successfully.","HealthCheckName":"Trace Mode","SourceContext":"Umbraco.Web.HealthCheck.HealthCheckResults","ProcessId":22260,"ProcessName":"iisexpress","ThreadId":41,"AppDomainId":2,"AppDomainAppId":"LMW3SVC2ROOT","MachineName":"AAR00112","Log4NetLevel":"INFO "}
{"@t":"2022-02-10T07:32:50.4938442Z","@mt":"Result for {HealthCheckName}: {HealthCheckResult}, Message: '{HealthCheckMessage}'","HealthCheckName":"Trace Mode","HealthCheckResult":"Success","HealthCheckMessage":"Trace mode is disabled.","SourceContext":"Umbraco.Web.HealthCheck.HealthCheckResults","ProcessId":22260,"ProcessName":"iisexpress","ThreadId":41,"AppDomainId":2,"AppDomainAppId":"LMW3SVC2ROOT","MachineName":"AAR00112","Log4NetLevel":"INFO "}
{"@t":"2022-02-10T07:32:50.4938442Z","@mt":"Checks for '{HealthCheckName}' all completed successfully.","HealthCheckName":"Debug Compilation Mode","SourceContext":"Umbraco.Web.HealthCheck.HealthCheckResults","ProcessId":22260,"ProcessName":"iisexpress","ThreadId":41,"AppDomainId":2,"AppDomainAppId":"LMW3SVC2ROOT","MachineName":"AAR00112","Log4NetLevel":"INFO "}
{"@t":"2022-02-10T07:32:50.4938442Z","@mt":"Result for {HealthCheckName}: {HealthCheckResult}, Message: '{HealthCheckMessage}'","HealthCheckName":"Debug Compilation Mode","HealthCheckResult":"Success","HealthCheckMessage":"Debug compilation mode is disabled.","SourceContext":"Umbraco.Web.HealthCheck.HealthCheckResults","ProcessId":22260,"ProcessName":"iisexpress","ThreadId":41,"AppDomainId":2,"AppDomainAppId":"LMW3SVC2ROOT","MachineName":"AAR00112","Log4NetLevel":"INFO "}
{"@t":"2022-02-10T07:47:43.6664052Z","@mt":"{StartMessage} [Timing {TimingId}]","StartMessage":"Booting Umbraco 8.17.2.","TimingId":"3c5855f","SourceContext":"Umbraco.Core.Runtime.CoreRuntime","ProcessId":24260,"ProcessName":"iisexpress","ThreadId":1,"AppDomainId":2,"AppDomainAppId":"LMW3SVC2ROOT","MachineName":"AAR00112","Log4NetLevel":"INFO ","HttpRequestNumber":1,"HttpRequestId":"f4db43e5-944d-4ec2-be9a-1bd77afe473f"}
{"@t":"2022-02-10T07:47:43.6964070Z","@mt":"Booting site '{HostingSiteName}', app '{HostingApplicationID}', path '{HostingPhysicalPath}', server '{MachineName}'.","HostingSiteName":"Flight2Orbit","HostingApplicationID":"/LM/W3SVC/2/ROOT","HostingPhysicalPath":"C:\\Users\\Elias.Geirdal.EMEA\\git\\FlightToOrbit\\BE\\Flight2Orbit\\","MachineName":"AAR00112","SourceContext":"Umbraco.Core.Runtime.CoreRuntime","ProcessId":24260,"ProcessName":"iisexpress","ThreadId":1,"AppDomainId":2,"AppDomainAppId":"LMW3SVC2ROOT","Log4NetLevel":"INFO ","HttpRequestNumber":1,"HttpRequestId":"f4db43e5-944d-4ec2-be9a-1bd77afe473f"}
{"@t":"2022-02-10T07:47:43.8514057Z","@mt":"Acquiring.","SourceContext":"Umbraco.Core.Runtime.MainDom","ProcessId":24260,"ProcessName":"iisexpress","ThreadId":1,"AppDomainId":2,"AppDomainAppId":"LMW3SVC2ROOT","MachineName":"AAR00112","Log4NetLevel":"INFO ","HttpRequestNumber":1,"HttpRequestId":"f4db43e5-944d-4ec2-be9a-1bd77afe473f"}
{"@t":"2022-02-10T07:47:43.8534103Z","@mt":"Acquired.","SourceContext":"Umbraco.Core.Runtime.MainDom","ProcessId":24260,"ProcessName":"iisexpress","ThreadId":1,"AppDomainId":2,"AppDomainAppId":"LMW3SVC2ROOT","MachineName":"AAR00112","Log4NetLevel":"INFO ","HttpRequestNumber":1,"HttpRequestId":"f4db43e5-944d-4ec2-be9a-1bd77afe473f"}
{"@t":"2022-02-10T07:47:44.9574103Z","@mt":"{StartMessage} [Timing {TimingId}]","StartMessage":"Resolving composer types.","TimingId":"707c0b7","SourceContext":"Umbraco.Core.Runtime.CoreRuntime","ProcessId":24260,"ProcessName":"iisexpress","ThreadId":1,"AppDomainId":2,"AppDomainAppId":"LMW3SVC2ROOT","MachineName":"AAR00112","Log4NetLevel":"INFO ","HttpRequestNumber":1,"HttpRequestId":"f4db43e5-944d-4ec2-be9a-1bd77afe473f"}
{"@t":"2022-02-10T07:47:45.1034125Z","@mt":"{EndMessage} ({Duration}ms) [Timing {TimingId}]","EndMessage":"Resolved.","Duration":144,"TimingId":"707c0b7","SourceContext":"Umbraco.Core.Runtime.CoreRuntime","ProcessId":24260,"ProcessName":"iisexpress","ThreadId":1,"AppDomainId":2,"AppDomainAppId":"LMW3SVC2ROOT","MachineName":"AAR00112","Log4NetLevel":"INFO ","HttpRequestNumber":1,"HttpRequestId":"f4db43e5-944d-4ec2-be9a-1bd77afe473f"}
{"@t":"2022-02-10T07:47:45.7404090Z","@mt":"Profiler is VoidProfiler, not profiling (must run debug mode to profile).","SourceContext":"Umbraco.Web.Logging.WebProfilerComponent","ProcessId":24260,"ProcessName":"iisexpress","ThreadId":1,"AppDomainId":2,"AppDomainAppId":"LMW3SVC2ROOT","MachineName":"AAR00112","Log4NetLevel":"INFO ","HttpRequestNumber":1,"HttpRequestId":"f4db43e5-944d-4ec2-be9a-1bd77afe473f"}
{"@t":"2022-02-10T07:47:45.9284090Z","@mt":"Initializing Umbraco internal event handlers for cache refreshing.","SourceContext":"Umbraco.Web.Cache.DistributedCacheBinderComponent","ProcessId":24260,"ProcessName":"iisexpress","ThreadId":1,"AppDomainId":2,"AppDomainAppId":"LMW3SVC2ROOT","MachineName":"AAR00112","Log4NetLevel":"INFO ","HttpRequestNumber":1,"HttpRequestId":"f4db43e5-944d-4ec2-be9a-1bd77afe473f"}
{"@t":"2022-02-10T07:47:46.0214078Z","@mt":"Adding examine event handlers for {RegisteredIndexers} index providers.","RegisteredIndexers":3,"SourceContext":"Umbraco.Web.Search.ExamineComponent","ProcessId":24260,"ProcessName":"iisexpress","ThreadId":1,"AppDomainId":2,"AppDomainAppId":"LMW3SVC2ROOT","MachineName":"AAR00112","Log4NetLevel":"INFO ","HttpRequestNumber":1,"HttpRequestId":"f4db43e5-944d-4ec2-be9a-1bd77afe473f"}
{"@t":"2022-02-10T07:47:46.0894130Z","@mt":"{EndMessage} ({Duration}ms) [Timing {TimingId}]","EndMessage":"Booted.","Duration":2439,"TimingId":"3c5855f","SourceContext":"Umbraco.Core.Runtime.CoreRuntime","ProcessId":24260,"ProcessName":"iisexpress","ThreadId":1,"AppDomainId":2,"AppDomainAppId":"LMW3SVC2ROOT","MachineName":"AAR00112","Log4NetLevel":"INFO ","HttpRequestNumber":1,"HttpRequestId":"f4db43e5-944d-4ec2-be9a-1bd77afe473f"}
{"@t":"2022-02-10T07:47:46.7934065Z","@mt":"New url {Url} detected, re-discovering application url.","Url":"http://localhost:54252/umbraco","SourceContext":"Umbraco.Core.Sync.ApplicationUrlHelper","ProcessId":24260,"ProcessName":"iisexpress","ThreadId":16,"AppDomainId":2,"AppDomainAppId":"LMW3SVC2ROOT","MachineName":"AAR00112","Log4NetLevel":"INFO ","HttpRequestNumber":2,"HttpRequestId":"8ed9a6bd-2ad1-4116-9eb5-1e370cee293a"}
{"@t":"2022-02-10T07:47:46.7964066Z","@mt":"ApplicationUrl: {UmbracoAppUrl} (UmbracoModule request)","UmbracoAppUrl":"http://localhost:54252/umbraco","SourceContext":"Umbraco.Core.Sync.ApplicationUrlHelper","ProcessId":24260,"ProcessName":"iisexpress","ThreadId":16,"AppDomainId":2,"AppDomainAppId":"LMW3SVC2ROOT","MachineName":"AAR00112","Log4NetLevel":"INFO ","HttpRequestNumber":2,"HttpRequestId":"8ed9a6bd-2ad1-4116-9eb5-1e370cee293a"}
{"@t":"2022-02-10T07:47:47.6064061Z","@mt":"Registered with MainDom, localContentDbExists? {LocalContentDbExists}, localMediaDbExists? {LocalMediaDbExists}","LocalContentDbExists":true,"LocalMediaDbExists":true,"SourceContext":"Umbraco.Web.PublishedCache.NuCache.PublishedSnapshotService","ProcessId":24260,"ProcessName":"iisexpress","ThreadId":16,"AppDomainId":2,"AppDomainAppId":"LMW3SVC2ROOT","MachineName":"AAR00112","Log4NetLevel":"INFO ","HttpRequestNumber":2,"HttpRequestId":"8ed9a6bd-2ad1-4116-9eb5-1e370cee293a"}
{"@t":"2022-02-10T07:47:47.6074083Z","@mt":"Creating the content store, localContentDbExists? {LocalContentDbExists}","LocalContentDbExists":true,"SourceContext":"Umbraco.Web.PublishedCache.NuCache.PublishedSnapshotService","ProcessId":24260,"ProcessName":"iisexpress","ThreadId":16,"AppDomainId":2,"AppDomainAppId":"LMW3SVC2ROOT","MachineName":"AAR00112","Log4NetLevel":"INFO ","HttpRequestNumber":2,"HttpRequestId":"8ed9a6bd-2ad1-4116-9eb5-1e370cee293a"}
{"@t":"2022-02-10T07:47:47.6094457Z","@mt":"Creating the media store, localMediaDbExists? {LocalMediaDbExists}","LocalMediaDbExists":true,"SourceContext":"Umbraco.Web.PublishedCache.NuCache.PublishedSnapshotService","ProcessId":24260,"ProcessName":"iisexpress","ThreadId":16,"AppDomainId":2,"AppDomainAppId":"LMW3SVC2ROOT","MachineName":"AAR00112","Log4NetLevel":"INFO ","HttpRequestNumber":2,"HttpRequestId":"8ed9a6bd-2ad1-4116-9eb5-1e370cee293a"}
{"@t":"2022-02-10T07:47:48.5994115Z","@mt":"{StartMessage} [Timing {TimingId}]","StartMessage":"Loading content from local cache file","TimingId":"d3adf45","SourceContext":"Umbraco.Web.PublishedCache.NuCache.PublishedSnapshotService","ProcessId":24260,"ProcessName":"iisexpress","ThreadId":16,"AppDomainId":2,"AppDomainAppId":"LMW3SVC2ROOT","MachineName":"AAR00112","Log4NetLevel":"INFO ","HttpRequestNumber":2,"HttpRequestId":"8ed9a6bd-2ad1-4116-9eb5-1e370cee293a"}
{"@t":"2022-02-10T07:47:48.6564116Z","@mt":"{EndMessage} ({Duration}ms) [Timing {TimingId}]","EndMessage":"Completed.","Duration":56,"TimingId":"d3adf45","SourceContext":"Umbraco.Web.PublishedCache.NuCache.PublishedSnapshotService","ProcessId":24260,"ProcessName":"iisexpress","ThreadId":16,"AppDomainId":2,"AppDomainAppId":"LMW3SVC2ROOT","MachineName":"AAR00112","Log4NetLevel":"INFO ","HttpRequestNumber":2,"HttpRequestId":"8ed9a6bd-2ad1-4116-9eb5-1e370cee293a"}
{"@t":"2022-02-10T07:47:48.6714141Z","@mt":"{StartMessage} [Timing {TimingId}]","StartMessage":"Loading media from local cache file","TimingId":"cb58d20","SourceContext":"Umbraco.Web.PublishedCache.NuCache.PublishedSnapshotService","ProcessId":24260,"ProcessName":"iisexpress","ThreadId":16,"AppDomainId":2,"AppDomainAppId":"LMW3SVC2ROOT","MachineName":"AAR00112","Log4NetLevel":"INFO ","HttpRequestNumber":2,"HttpRequestId":"8ed9a6bd-2ad1-4116-9eb5-1e370cee293a"}
{"@t":"2022-02-10T07:47:48.6724102Z","@mt":"{EndMessage} ({Duration}ms) [Timing {TimingId}]","EndMessage":"Completed.","Duration":1,"TimingId":"cb58d20","SourceContext":"Umbraco.Web.PublishedCache.NuCache.PublishedSnapshotService","ProcessId":24260,"ProcessName":"iisexpress","ThreadId":16,"AppDomainId":2,"AppDomainAppId":"LMW3SVC2ROOT","MachineName":"AAR00112","Log4NetLevel":"INFO ","HttpRequestNumber":2,"HttpRequestId":"8ed9a6bd-2ad1-4116-9eb5-1e370cee293a"}
{"@t":"2022-02-10T07:47:49.1034089Z","@mt":"Forcing index {IndexerName} to be unlocked since it was left in a locked state","IndexerName":"InternalIndex","SourceContext":"Umbraco.Examine.ExamineExtensions","ProcessId":24260,"ProcessName":"iisexpress","ThreadId":16,"AppDomainId":2,"AppDomainAppId":"LMW3SVC2ROOT","MachineName":"AAR00112","Log4NetLevel":"INFO ","HttpRequestNumber":2,"HttpRequestId":"8ed9a6bd-2ad1-4116-9eb5-1e370cee293a"}
{"@t":"2022-02-10T07:47:49.1044078Z","@mt":"Forcing index {IndexerName} to be unlocked since it was left in a locked state","IndexerName":"MembersIndex","SourceContext":"Umbraco.Examine.ExamineExtensions","ProcessId":24260,"ProcessName":"iisexpress","ThreadId":16,"AppDomainId":2,"AppDomainAppId":"LMW3SVC2ROOT","MachineName":"AAR00112","Log4NetLevel":"INFO ","HttpRequestNumber":2,"HttpRequestId":"8ed9a6bd-2ad1-4116-9eb5-1e370cee293a"}
{"@t":"2022-02-10T07:47:49.1054119Z","@mt":"Forcing index {IndexerName} to be unlocked since it was left in a locked state","IndexerName":"ExternalIndex","SourceContext":"Umbraco.Examine.ExamineExtensions","ProcessId":24260,"ProcessName":"iisexpress","ThreadId":16,"AppDomainId":2,"AppDomainAppId":"LMW3SVC2ROOT","MachineName":"AAR00112","Log4NetLevel":"INFO ","HttpRequestNumber":2,"HttpRequestId":"8ed9a6bd-2ad1-4116-9eb5-1e370cee293a"}
{"@t":"2022-02-10T07:47:49.1074093Z","@mt":"Starting initialize async background thread.","SourceContext":"Umbraco.Web.Search.BackgroundIndexRebuilder","ProcessId":24260,"ProcessName":"iisexpress","ThreadId":16,"AppDomainId":2,"AppDomainAppId":"LMW3SVC2ROOT","MachineName":"AAR00112","Log4NetLevel":"INFO ","HttpRequestNumber":2,"HttpRequestId":"8ed9a6bd-2ad1-4116-9eb5-1e370cee293a"}
{"@t":"2022-02-10T07:48:03.3620143Z","@mt":"{LogPrefix} Terminating {Immediate}","LogPrefix":"[TelemetryReporter] ","Immediate":"","SourceContext":"Umbraco.Web.Scheduling.BackgroundTaskRunner","ProcessId":24260,"ProcessName":"iisexpress","ThreadId":5,"AppDomainId":2,"AppDomainAppId":"LMW3SVC2ROOT","MachineName":"AAR00112","Log4NetLevel":"INFO "}
{"@t":"2022-02-10T07:48:03.3620143Z","@mt":"{LogPrefix} Terminating {Immediate}","LogPrefix":"[ServerRegistration] ","Immediate":"","SourceContext":"Umbraco.Web.Scheduling.BackgroundTaskRunner","ProcessId":24260,"ProcessName":"iisexpress","ThreadId":5,"AppDomainId":2,"AppDomainAppId":"LMW3SVC2ROOT","MachineName":"AAR00112","Log4NetLevel":"INFO "}
{"@t":"2022-02-10T07:48:03.3620143Z","@mt":"{LogPrefix} Terminating {Immediate}","LogPrefix":"[ScheduledPublishing] ","Immediate":"","SourceContext":"Umbraco.Web.Scheduling.BackgroundTaskRunner","ProcessId":24260,"ProcessName":"iisexpress","ThreadId":5,"AppDomainId":2,"AppDomainAppId":"LMW3SVC2ROOT","MachineName":"AAR00112","Log4NetLevel":"INFO "}
{"@t":"2022-02-10T07:48:03.3620143Z","@mt":"{LogPrefix} Terminating {Immediate}","LogPrefix":"[ServerInstProcess] ","Immediate":"","SourceContext":"Umbraco.Web.Scheduling.BackgroundTaskRunner","ProcessId":24260,"ProcessName":"iisexpress","ThreadId":5,"AppDomainId":2,"AppDomainAppId":"LMW3SVC2ROOT","MachineName":"AAR00112","Log4NetLevel":"INFO "}
{"@t":"2022-02-10T07:48:03.3680130Z","@mt":"Stopping ({SignalSource})","SignalSource":"environment","SourceContext":"Umbraco.Core.Runtime.MainDom","ProcessId":24260,"ProcessName":"iisexpress","ThreadId":5,"AppDomainId":2,"AppDomainAppId":"LMW3SVC2ROOT","MachineName":"AAR00112","Log4NetLevel":"INFO "}
{"@t":"2022-02-10T07:48:03.3690132Z","@mt":"{LogPrefix} Canceling tasks","LogPrefix":"[TelemetryReporter] ","SourceContext":"Umbraco.Web.Scheduling.BackgroundTaskRunner","ProcessId":24260,"ProcessName":"iisexpress","ThreadId":12,"AppDomainId":2,"AppDomainAppId":"LMW3SVC2ROOT","MachineName":"AAR00112","Log4NetLevel":"INFO "}
{"@t":"2022-02-10T07:48:03.3710128Z","@mt":"{LogPrefix} Tasks {TaskStatus}, terminated","LogPrefix":"[TelemetryReporter] ","TaskStatus":"cancelled","SourceContext":"Umbraco.Web.Scheduling.BackgroundTaskRunner","ProcessId":24260,"ProcessName":"iisexpress","ThreadId":12,"AppDomainId":2,"AppDomainAppId":"LMW3SVC2ROOT","MachineName":"AAR00112","Log4NetLevel":"INFO "}
{"@t":"2022-02-10T07:48:03.3710128Z","@mt":"{LogPrefix} Canceling tasks","LogPrefix":"[ServerRegistration] ","SourceContext":"Umbraco.Web.Scheduling.BackgroundTaskRunner","ProcessId":24260,"ProcessName":"iisexpress","ThreadId":12,"AppDomainId":2,"AppDomainAppId":"LMW3SVC2ROOT","MachineName":"AAR00112","Log4NetLevel":"INFO "}
{"@t":"2022-02-10T07:48:03.3710128Z","@mt":"{LogPrefix} Tasks {TaskStatus}, terminated","LogPrefix":"[ServerRegistration] ","TaskStatus":"cancelled","SourceContext":"Umbraco.Web.Scheduling.BackgroundTaskRunner","ProcessId":24260,"ProcessName":"iisexpress","ThreadId":12,"AppDomainId":2,"AppDomainAppId":"LMW3SVC2ROOT","MachineName":"AAR00112","Log4NetLevel":"INFO "}
{"@t":"2022-02-10T07:48:03.3710128Z","@mt":"{LogPrefix} Canceling tasks","LogPrefix":"[ServerInstProcess] ","SourceContext":"Umbraco.Web.Scheduling.BackgroundTaskRunner","ProcessId":24260,"ProcessName":"iisexpress","ThreadId":12,"AppDomainId":2,"AppDomainAppId":"LMW3SVC2ROOT","MachineName":"AAR00112","Log4NetLevel":"INFO "}
{"@t":"2022-02-10T07:48:03.3710128Z","@mt":"{LogPrefix} Tasks {TaskStatus}, terminated","LogPrefix":"[ServerInstProcess] ","TaskStatus":"cancelled","SourceContext":"Umbraco.Web.Scheduling.BackgroundTaskRunner","ProcessId":24260,"ProcessName":"iisexpress","ThreadId":12,"AppDomainId":2,"AppDomainAppId":"LMW3SVC2ROOT","MachineName":"AAR00112","Log4NetLevel":"INFO "}
{"@t":"2022-02-10T07:48:03.3710128Z","@mt":"{LogPrefix} Canceling tasks","LogPrefix":"[ScheduledPublishing] ","SourceContext":"Umbraco.Web.Scheduling.BackgroundTaskRunner","ProcessId":24260,"ProcessName":"iisexpress","ThreadId":12,"AppDomainId":2,"AppDomainAppId":"LMW3SVC2ROOT","MachineName":"AAR00112","Log4NetLevel":"INFO "}
{"@t":"2022-02-10T07:48:03.3710128Z","@mt":"{LogPrefix} Tasks {TaskStatus}, terminated","LogPrefix":"[ScheduledPublishing] ","TaskStatus":"cancelled","SourceContext":"Umbraco.Web.Scheduling.BackgroundTaskRunner","ProcessId":24260,"ProcessName":"iisexpress","ThreadId":12,"AppDomainId":2,"AppDomainAppId":"LMW3SVC2ROOT","MachineName":"AAR00112","Log4NetLevel":"INFO "}
{"@t":"2022-02-10T07:48:03.3870132Z","@mt":"{StartMessage} [Timing {TimingId}]","StartMessage":"Examine shutting down","TimingId":"e878daa","SourceContext":"Umbraco.Web.Search.ExamineComponent","ProcessId":24260,"ProcessName":"iisexpress","ThreadId":5,"AppDomainId":2,"AppDomainAppId":"LMW3SVC2ROOT","MachineName":"AAR00112","Log4NetLevel":"INFO "}
{"@t":"2022-02-10T07:48:03.4240169Z","@mt":"{EndMessage} ({Duration}ms) [Timing {TimingId}]","EndMessage":"Completed.","Duration":36,"TimingId":"e878daa","SourceContext":"Umbraco.Web.Search.ExamineComponent","ProcessId":24260,"ProcessName":"iisexpress","ThreadId":5,"AppDomainId":2,"AppDomainAppId":"LMW3SVC2ROOT","MachineName":"AAR00112","Log4NetLevel":"INFO "}
{"@t":"2022-02-10T07:48:03.6080115Z","@mt":"Released from MainDom","SourceContext":"Umbraco.Web.PublishedCache.NuCache.PublishedSnapshotService","ProcessId":24260,"ProcessName":"iisexpress","ThreadId":5,"AppDomainId":2,"AppDomainAppId":"LMW3SVC2ROOT","MachineName":"AAR00112","Log4NetLevel":"INFO "}
{"@t":"2022-02-10T07:48:03.6100131Z","@mt":"Released ({SignalSource})","SignalSource":"environment","SourceContext":"Umbraco.Core.Runtime.MainDom","ProcessId":24260,"ProcessName":"iisexpress","ThreadId":5,"AppDomainId":2,"AppDomainAppId":"LMW3SVC2ROOT","MachineName":"AAR00112","Log4NetLevel":"INFO "}
{"@t":"2022-02-10T07:48:03.6110122Z","@mt":"{LogPrefix} Terminating {Immediate}","LogPrefix":"[TempFileCleanup] ","Immediate":"","SourceContext":"Umbraco.Web.Scheduling.BackgroundTaskRunner","ProcessId":24260,"ProcessName":"iisexpress","ThreadId":5,"AppDomainId":2,"AppDomainAppId":"LMW3SVC2ROOT","MachineName":"AAR00112","Log4NetLevel":"INFO "}
{"@t":"2022-02-10T07:48:03.6110122Z","@mt":"{LogPrefix} Canceling tasks","LogPrefix":"[TempFileCleanup] ","SourceContext":"Umbraco.Web.Scheduling.BackgroundTaskRunner","ProcessId":24260,"ProcessName":"iisexpress","ThreadId":12,"AppDomainId":2,"AppDomainAppId":"LMW3SVC2ROOT","MachineName":"AAR00112","Log4NetLevel":"INFO "}
{"@t":"2022-02-10T07:48:03.6110122Z","@mt":"{LogPrefix} Tasks {TaskStatus}, terminated","LogPrefix":"[TempFileCleanup] ","TaskStatus":"cancelled","SourceContext":"Umbraco.Web.Scheduling.BackgroundTaskRunner","ProcessId":24260,"ProcessName":"iisexpress","ThreadId":12,"AppDomainId":2,"AppDomainAppId":"LMW3SVC2ROOT","MachineName":"AAR00112","Log4NetLevel":"INFO "}
{"@t":"2022-02-10T07:48:03.6110122Z","@mt":"{LogPrefix} Terminating {Immediate}","LogPrefix":"[ScheduledTasks] ","Immediate":"","SourceContext":"Umbraco.Web.Scheduling.BackgroundTaskRunner","ProcessId":24260,"ProcessName":"iisexpress","ThreadId":5,"AppDomainId":2,"AppDomainAppId":"LMW3SVC2ROOT","MachineName":"AAR00112","Log4NetLevel":"INFO "}
{"@t":"2022-02-10T07:48:03.6110122Z","@mt":"{LogPrefix} Terminating {Immediate}","LogPrefix":"[KeepAlive] ","Immediate":"","SourceContext":"Umbraco.Web.Scheduling.BackgroundTaskRunner","ProcessId":24260,"ProcessName":"iisexpress","ThreadId":5,"AppDomainId":2,"AppDomainAppId":"LMW3SVC2ROOT","MachineName":"AAR00112","Log4NetLevel":"INFO "}
{"@t":"2022-02-10T07:48:03.6160130Z","@mt":"{LogPrefix} Canceling tasks","LogPrefix":"[ScheduledTasks] ","SourceContext":"Umbraco.Web.Scheduling.BackgroundTaskRunner","ProcessId":24260,"ProcessName":"iisexpress","ThreadId":12,"AppDomainId":2,"AppDomainAppId":"LMW3SVC2ROOT","MachineName":"AAR00112","Log4NetLevel":"INFO "}
{"@t":"2022-02-10T07:48:03.6160130Z","@mt":"{LogPrefix} Tasks {TaskStatus}, terminated","LogPrefix":"[ScheduledTasks] ","TaskStatus":"cancelled","SourceContext":"Umbraco.Web.Scheduling.BackgroundTaskRunner","ProcessId":24260,"ProcessName":"iisexpress","ThreadId":12,"AppDomainId":2,"AppDomainAppId":"LMW3SVC2ROOT","MachineName":"AAR00112","Log4NetLevel":"INFO "}
{"@t":"2022-02-10T07:48:03.6230209Z","@mt":"{LogPrefix} Terminating {Immediate}","LogPrefix":"[LogScrubber] ","Immediate":"","SourceContext":"Umbraco.Web.Scheduling.BackgroundTaskRunner","ProcessId":24260,"ProcessName":"iisexpress","ThreadId":5,"AppDomainId":2,"AppDomainAppId":"LMW3SVC2ROOT","MachineName":"AAR00112","Log4NetLevel":"INFO "}
{"@t":"2022-02-10T07:48:03.6230209Z","@mt":"{LogPrefix} Terminating {Immediate}","LogPrefix":"[Umbraco.Web.Scheduling.IBackgroundTask] ","Immediate":"","SourceContext":"Umbraco.Web.Scheduling.BackgroundTaskRunner","ProcessId":24260,"ProcessName":"iisexpress","ThreadId":5,"AppDomainId":2,"AppDomainAppId":"LMW3SVC2ROOT","MachineName":"AAR00112","Log4NetLevel":"INFO "}
{"@t":"2022-02-10T07:48:03.6230209Z","@mt":"{LogPrefix} Terminating {Immediate}","LogPrefix":"[RebuildIndexesOnStartup] ","Immediate":"","SourceContext":"Umbraco.Web.Scheduling.BackgroundTaskRunner","ProcessId":24260,"ProcessName":"iisexpress","ThreadId":5,"AppDomainId":2,"AppDomainAppId":"LMW3SVC2ROOT","MachineName":"AAR00112","Log4NetLevel":"INFO "}
{"@t":"2022-02-10T07:48:03.6230209Z","@mt":"{LogPrefix} Terminating {Immediate}","LogPrefix":"[HealthCheckNotifier] ","Immediate":"","SourceContext":"Umbraco.Web.Scheduling.BackgroundTaskRunner","ProcessId":24260,"ProcessName":"iisexpress","ThreadId":5,"AppDomainId":2,"AppDomainAppId":"LMW3SVC2ROOT","MachineName":"AAR00112","Log4NetLevel":"INFO "}
{"@t":"2022-02-10T07:48:05.3810139Z","@mt":"{LogPrefix} Canceling tasks","LogPrefix":"[ServerRegistration] ","SourceContext":"Umbraco.Web.Scheduling.BackgroundTaskRunner","ProcessId":24260,"ProcessName":"iisexpress","ThreadId":15,"AppDomainId":2,"AppDomainAppId":"LMW3SVC2ROOT","MachineName":"AAR00112","Log4NetLevel":"INFO "}
{"@t":"2022-02-10T07:48:05.3880139Z","@mt":"{LogPrefix} Canceling tasks","LogPrefix":"[KeepAlive] ","SourceContext":"Umbraco.Web.Scheduling.BackgroundTaskRunner","ProcessId":24260,"ProcessName":"iisexpress","ThreadId":15,"AppDomainId":2,"AppDomainAppId":"LMW3SVC2ROOT","MachineName":"AAR00112","Log4NetLevel":"INFO "}
{"@t":"2022-02-10T07:48:05.3880139Z","@mt":"{LogPrefix} Tasks {TaskStatus}, terminated","LogPrefix":"[KeepAlive] ","TaskStatus":"cancelled","SourceContext":"Umbraco.Web.Scheduling.BackgroundTaskRunner","ProcessId":24260,"ProcessName":"iisexpress","ThreadId":15,"AppDomainId":2,"AppDomainAppId":"LMW3SVC2ROOT","MachineName":"AAR00112","Log4NetLevel":"INFO "}
{"@t":"2022-02-10T07:48:05.4020141Z","@mt":"{LogPrefix} Canceling tasks","LogPrefix":"[ScheduledPublishing] ","SourceContext":"Umbraco.Web.Scheduling.BackgroundTaskRunner","ProcessId":24260,"ProcessName":"iisexpress","ThreadId":10,"AppDomainId":2,"AppDomainAppId":"LMW3SVC2ROOT","MachineName":"AAR00112","Log4NetLevel":"INFO "}
{"@t":"2022-02-10T07:48:05.4060167Z","@mt":"{LogPrefix} Canceling tasks","LogPrefix":"[LogScrubber] ","SourceContext":"Umbraco.Web.Scheduling.BackgroundTaskRunner","ProcessId":24260,"ProcessName":"iisexpress","ThreadId":10,"AppDomainId":2,"AppDomainAppId":"LMW3SVC2ROOT","MachineName":"AAR00112","Log4NetLevel":"INFO "}
{"@t":"2022-02-10T07:48:05.4060167Z","@mt":"{LogPrefix} Tasks {TaskStatus}, terminated","LogPrefix":"[LogScrubber] ","TaskStatus":"cancelled","SourceContext":"Umbraco.Web.Scheduling.BackgroundTaskRunner","ProcessId":24260,"ProcessName":"iisexpress","ThreadId":10,"AppDomainId":2,"AppDomainAppId":"LMW3SVC2ROOT","MachineName":"AAR00112","Log4NetLevel":"INFO "}
{"@t":"2022-02-10T07:48:05.4060167Z","@mt":"{LogPrefix} Canceling tasks","LogPrefix":"[Umbraco.Web.Scheduling.IBackgroundTask] ","SourceContext":"Umbraco.Web.Scheduling.BackgroundTaskRunner","ProcessId":24260,"ProcessName":"iisexpress","ThreadId":10,"AppDomainId":2,"AppDomainAppId":"LMW3SVC2ROOT","MachineName":"AAR00112","Log4NetLevel":"INFO "}
{"@t":"2022-02-10T07:48:05.4060167Z","@mt":"{LogPrefix} Tasks {TaskStatus}, terminated","LogPrefix":"[Umbraco.Web.Scheduling.IBackgroundTask] ","TaskStatus":"cancelled","SourceContext":"Umbraco.Web.Scheduling.BackgroundTaskRunner","ProcessId":24260,"ProcessName":"iisexpress","ThreadId":10,"AppDomainId":2,"AppDomainAppId":"LMW3SVC2ROOT","MachineName":"AAR00112","Log4NetLevel":"INFO "}
{"@t":"2022-02-10T07:48:05.4060167Z","@mt":"{LogPrefix} Canceling tasks","LogPrefix":"[ServerInstProcess] ","SourceContext":"Umbraco.Web.Scheduling.BackgroundTaskRunner","ProcessId":24260,"ProcessName":"iisexpress","ThreadId":13,"AppDomainId":2,"AppDomainAppId":"LMW3SVC2ROOT","MachineName":"AAR00112","Log4NetLevel":"INFO "}
{"@t":"2022-02-10T07:48:05.4060167Z","@mt":"{LogPrefix} Canceling tasks","LogPrefix":"[TelemetryReporter] ","SourceContext":"Umbraco.Web.Scheduling.BackgroundTaskRunner","ProcessId":24260,"ProcessName":"iisexpress","ThreadId":14,"AppDomainId":2,"AppDomainAppId":"LMW3SVC2ROOT","MachineName":"AAR00112","Log4NetLevel":"INFO "}
{"@t":"2022-02-10T07:48:05.6160190Z","@mt":"{LogPrefix} Canceling tasks","LogPrefix":"[TempFileCleanup] ","SourceContext":"Umbraco.Web.Scheduling.BackgroundTaskRunner","ProcessId":24260,"ProcessName":"iisexpress","ThreadId":11,"AppDomainId":2,"AppDomainAppId":"LMW3SVC2ROOT","MachineName":"AAR00112","Log4NetLevel":"INFO "}
{"@t":"2022-02-10T07:48:05.6310139Z","@mt":"{LogPrefix} Canceling tasks","LogPrefix":"[ScheduledTasks] ","SourceContext":"Umbraco.Web.Scheduling.BackgroundTaskRunner","ProcessId":24260,"ProcessName":"iisexpress","ThreadId":12,"AppDomainId":2,"AppDomainAppId":"LMW3SVC2ROOT","MachineName":"AAR00112","Log4NetLevel":"INFO "}
{"@t":"2022-02-10T07:48:05.6320134Z","@mt":"{LogPrefix} Canceling tasks","LogPrefix":"[HealthCheckNotifier] ","SourceContext":"Umbraco.Web.Scheduling.BackgroundTaskRunner","ProcessId":24260,"ProcessName":"iisexpress","ThreadId":12,"AppDomainId":2,"AppDomainAppId":"LMW3SVC2ROOT","MachineName":"AAR00112","Log4NetLevel":"INFO "}
{"@t":"2022-02-10T07:48:05.6320134Z","@mt":"{LogPrefix} Tasks {TaskStatus}, terminated","LogPrefix":"[HealthCheckNotifier] ","TaskStatus":"cancelled","SourceContext":"Umbraco.Web.Scheduling.BackgroundTaskRunner","ProcessId":24260,"ProcessName":"iisexpress","ThreadId":12,"AppDomainId":2,"AppDomainAppId":"LMW3SVC2ROOT","MachineName":"AAR00112","Log4NetLevel":"INFO "}
{"@t":"2022-02-10T07:48:06.6640112Z","@mt":"{LogPrefix} Canceling tasks","LogPrefix":"[KeepAlive] ","SourceContext":"Umbraco.Web.Scheduling.BackgroundTaskRunner","ProcessId":24260,"ProcessName":"iisexpress","ThreadId":16,"AppDomainId":2,"AppDomainAppId":"LMW3SVC2ROOT","MachineName":"AAR00112","Log4NetLevel":"INFO "}
{"@t":"2022-02-10T07:48:07.3950151Z","@mt":"{LogPrefix} Canceling tasks","LogPrefix":"[LogScrubber] ","SourceContext":"Umbraco.Web.Scheduling.BackgroundTaskRunner","ProcessId":24260,"ProcessName":"iisexpress","ThreadId":15,"AppDomainId":2,"AppDomainAppId":"LMW3SVC2ROOT","MachineName":"AAR00112","Log4NetLevel":"INFO "}
{"@t":"2022-02-10T07:48:07.4110146Z","@mt":"{LogPrefix} Canceling tasks","LogPrefix":"[HealthCheckNotifier] ","SourceContext":"Umbraco.Web.Scheduling.BackgroundTaskRunner","ProcessId":24260,"ProcessName":"iisexpress","ThreadId":14,"AppDomainId":2,"AppDomainAppId":"LMW3SVC2ROOT","MachineName":"AAR00112","Log4NetLevel":"INFO "}
{"@t":"2022-02-10T07:48:07.4210159Z","@mt":"{LogPrefix} Canceling tasks","LogPrefix":"[RebuildIndexesOnStartup] ","SourceContext":"Umbraco.Web.Scheduling.BackgroundTaskRunner","ProcessId":24260,"ProcessName":"iisexpress","ThreadId":13,"AppDomainId":2,"AppDomainAppId":"LMW3SVC2ROOT","MachineName":"AAR00112","Log4NetLevel":"INFO "}
{"@t":"2022-02-10T07:48:07.4210159Z","@mt":"{LogPrefix} Canceling tasks","LogPrefix":"[Umbraco.Web.Scheduling.IBackgroundTask] ","SourceContext":"Umbraco.Web.Scheduling.BackgroundTaskRunner","ProcessId":24260,"ProcessName":"iisexpress","ThreadId":10,"AppDomainId":2,"AppDomainAppId":"LMW3SVC2ROOT","MachineName":"AAR00112","Log4NetLevel":"INFO "}
{"@t":"2022-02-10T07:48:08.1160173Z","@mt":"{StartMessage} [Timing {TimingId}]","StartMessage":"Booting Umbraco 8.17.2.","TimingId":"b722123","SourceContext":"Umbraco.Core.Runtime.CoreRuntime","ProcessId":24260,"ProcessName":"iisexpress","ThreadId":23,"AppDomainId":3,"AppDomainAppId":"LMW3SVC2ROOT","MachineName":"AAR00112","Log4NetLevel":"INFO ","HttpRequestNumber":1,"HttpRequestId":"245d39dd-2e19-4083-8f37-e65dc9d9cf7c"}
{"@t":"2022-02-10T07:48:08.1320107Z","@mt":"Booting site '{HostingSiteName}', app '{HostingApplicationID}', path '{HostingPhysicalPath}', server '{MachineName}'.","HostingSiteName":"Flight2Orbit","HostingApplicationID":"/LM/W3SVC/2/ROOT","HostingPhysicalPath":"C:\\Users\\Elias.Geirdal.EMEA\\git\\FlightToOrbit\\BE\\Flight2Orbit\\","MachineName":"AAR00112","SourceContext":"Umbraco.Core.Runtime.CoreRuntime","ProcessId":24260,"ProcessName":"iisexpress","ThreadId":23,"AppDomainId":3,"AppDomainAppId":"LMW3SVC2ROOT","Log4NetLevel":"INFO ","HttpRequestNumber":1,"HttpRequestId":"245d39dd-2e19-4083-8f37-e65dc9d9cf7c"}
{"@t":"2022-02-10T07:48:08.2870159Z","@mt":"Acquiring.","SourceContext":"Umbraco.Core.Runtime.MainDom","ProcessId":24260,"ProcessName":"iisexpress","ThreadId":23,"AppDomainId":3,"AppDomainAppId":"LMW3SVC2ROOT","MachineName":"AAR00112","Log4NetLevel":"INFO ","HttpRequestNumber":1,"HttpRequestId":"245d39dd-2e19-4083-8f37-e65dc9d9cf7c"}
{"@t":"2022-02-10T07:48:08.2930139Z","@mt":"Acquired.","SourceContext":"Umbraco.Core.Runtime.MainDom","ProcessId":24260,"ProcessName":"iisexpress","ThreadId":23,"AppDomainId":3,"AppDomainAppId":"LMW3SVC2ROOT","MachineName":"AAR00112","Log4NetLevel":"INFO ","HttpRequestNumber":1,"HttpRequestId":"245d39dd-2e19-4083-8f37-e65dc9d9cf7c"}
{"@t":"2022-02-10T07:48:08.8740121Z","@mt":"{StartMessage} [Timing {TimingId}]","StartMessage":"Resolving composer types.","TimingId":"a7cfaac","SourceContext":"Umbraco.Core.Runtime.CoreRuntime","ProcessId":24260,"ProcessName":"iisexpress","ThreadId":23,"AppDomainId":3,"AppDomainAppId":"LMW3SVC2ROOT","MachineName":"AAR00112","Log4NetLevel":"INFO ","HttpRequestNumber":1,"HttpRequestId":"245d39dd-2e19-4083-8f37-e65dc9d9cf7c"}
{"@t":"2022-02-10T07:48:09.0750141Z","@mt":"{EndMessage} ({Duration}ms) [Timing {TimingId}]","EndMessage":"Resolved.","Duration":200,"TimingId":"a7cfaac","SourceContext":"Umbraco.Core.Runtime.CoreRuntime","ProcessId":24260,"ProcessName":"iisexpress","ThreadId":23,"AppDomainId":3,"AppDomainAppId":"LMW3SVC2ROOT","MachineName":"AAR00112","Log4NetLevel":"INFO ","HttpRequestNumber":1,"HttpRequestId":"245d39dd-2e19-4083-8f37-e65dc9d9cf7c"}
{"@t":"2022-02-10T07:48:12.7320872Z","@mt":"Profiler is VoidProfiler, not profiling (must run debug mode to profile).","SourceContext":"Umbraco.Web.Logging.WebProfilerComponent","ProcessId":24260,"ProcessName":"iisexpress","ThreadId":23,"AppDomainId":3,"AppDomainAppId":"LMW3SVC2ROOT","MachineName":"AAR00112","Log4NetLevel":"INFO ","HttpRequestNumber":1,"HttpRequestId":"245d39dd-2e19-4083-8f37-e65dc9d9cf7c"}
{"@t":"2022-02-10T07:48:12.8740830Z","@mt":"Initializing Umbraco internal event handlers for cache refreshing.","SourceContext":"Umbraco.Web.Cache.DistributedCacheBinderComponent","ProcessId":24260,"ProcessName":"iisexpress","ThreadId":23,"AppDomainId":3,"AppDomainAppId":"LMW3SVC2ROOT","MachineName":"AAR00112","Log4NetLevel":"INFO ","HttpRequestNumber":1,"HttpRequestId":"245d39dd-2e19-4083-8f37-e65dc9d9cf7c"}
{"@t":"2022-02-10T07:48:12.9750820Z","@mt":"Adding examine event handlers for {RegisteredIndexers} index providers.","RegisteredIndexers":3,"SourceContext":"Umbraco.Web.Search.ExamineComponent","ProcessId":24260,"ProcessName":"iisexpress","ThreadId":23,"AppDomainId":3,"AppDomainAppId":"LMW3SVC2ROOT","MachineName":"AAR00112","Log4NetLevel":"INFO ","HttpRequestNumber":1,"HttpRequestId":"245d39dd-2e19-4083-8f37-e65dc9d9cf7c"}
{"@t":"2022-02-10T07:48:13.0300859Z","@mt":"{EndMessage} ({Duration}ms) [Timing {TimingId}]","EndMessage":"Booted.","Duration":4933,"TimingId":"b722123","SourceContext":"Umbraco.Core.Runtime.CoreRuntime","ProcessId":24260,"ProcessName":"iisexpress","ThreadId":23,"AppDomainId":3,"AppDomainAppId":"LMW3SVC2ROOT","MachineName":"AAR00112","Log4NetLevel":"INFO ","HttpRequestNumber":1,"HttpRequestId":"245d39dd-2e19-4083-8f37-e65dc9d9cf7c"}
{"@t":"2022-02-10T07:48:13.2610851Z","@mt":"New url {Url} detected, re-discovering application url.","Url":"http://localhost:54252/umbraco","SourceContext":"Umbraco.Core.Sync.ApplicationUrlHelper","ProcessId":24260,"ProcessName":"iisexpress","ThreadId":12,"AppDomainId":3,"AppDomainAppId":"LMW3SVC2ROOT","MachineName":"AAR00112","Log4NetLevel":"INFO ","HttpRequestNumber":2,"HttpRequestId":"36508350-2fd7-428a-9af5-2e50072fe903"}
{"@t":"2022-02-10T07:48:13.2610851Z","@mt":"New url {Url} detected, re-discovering application url.","Url":"http://localhost:54252/umbraco","SourceContext":"Umbraco.Core.Sync.ApplicationUrlHelper","ProcessId":24260,"ProcessName":"iisexpress","ThreadId":15,"AppDomainId":3,"AppDomainAppId":"LMW3SVC2ROOT","MachineName":"AAR00112","Log4NetLevel":"INFO ","HttpRequestNumber":3,"HttpRequestId":"d54778bf-69dc-4f18-be69-5afa9cfa20b6"}
{"@t":"2022-02-10T07:48:13.2630853Z","@mt":"ApplicationUrl: {UmbracoAppUrl} (UmbracoModule request)","UmbracoAppUrl":"http://localhost:54252/umbraco","SourceContext":"Umbraco.Core.Sync.ApplicationUrlHelper","ProcessId":24260,"ProcessName":"iisexpress","ThreadId":12,"AppDomainId":3,"AppDomainAppId":"LMW3SVC2ROOT","MachineName":"AAR00112","Log4NetLevel":"INFO ","HttpRequestNumber":2,"HttpRequestId":"36508350-2fd7-428a-9af5-2e50072fe903"}
{"@t":"2022-02-10T07:48:13.2630853Z","@mt":"ApplicationUrl: {UmbracoAppUrl} (UmbracoModule request)","UmbracoAppUrl":"http://localhost:54252/umbraco","SourceContext":"Umbraco.Core.Sync.ApplicationUrlHelper","ProcessId":24260,"ProcessName":"iisexpress","ThreadId":15,"AppDomainId":3,"AppDomainAppId":"LMW3SVC2ROOT","MachineName":"AAR00112","Log4NetLevel":"INFO ","HttpRequestNumber":3,"HttpRequestId":"d54778bf-69dc-4f18-be69-5afa9cfa20b6"}
{"@t":"2022-02-10T07:48:13.7250831Z","@mt":"Starting initialize async background thread.","SourceContext":"Umbraco.Web.Search.BackgroundIndexRebuilder","ProcessId":24260,"ProcessName":"iisexpress","ThreadId":15,"AppDomainId":3,"AppDomainAppId":"LMW3SVC2ROOT","MachineName":"AAR00112","Log4NetLevel":"INFO ","HttpRequestNumber":3,"HttpRequestId":"d54778bf-69dc-4f18-be69-5afa9cfa20b6"}
{"@t":"2022-02-10T07:48:13.8561247Z","@mt":"Registered with MainDom, localContentDbExists? {LocalContentDbExists}, localMediaDbExists? {LocalMediaDbExists}","LocalContentDbExists":true,"LocalMediaDbExists":true,"SourceContext":"Umbraco.Web.PublishedCache.NuCache.PublishedSnapshotService","ProcessId":24260,"ProcessName":"iisexpress","ThreadId":15,"AppDomainId":3,"AppDomainAppId":"LMW3SVC2ROOT","MachineName":"AAR00112","Log4NetLevel":"INFO ","HttpRequestNumber":3,"HttpRequestId":"d54778bf-69dc-4f18-be69-5afa9cfa20b6"}
{"@t":"2022-02-10T07:48:13.8571042Z","@mt":"Creating the content store, localContentDbExists? {LocalContentDbExists}","LocalContentDbExists":true,"SourceContext":"Umbraco.Web.PublishedCache.NuCache.PublishedSnapshotService","ProcessId":24260,"ProcessName":"iisexpress","ThreadId":15,"AppDomainId":3,"AppDomainAppId":"LMW3SVC2ROOT","MachineName":"AAR00112","Log4NetLevel":"INFO ","HttpRequestNumber":3,"HttpRequestId":"d54778bf-69dc-4f18-be69-5afa9cfa20b6"}
{"@t":"2022-02-10T07:48:13.8580823Z","@mt":"Creating the media store, localMediaDbExists? {LocalMediaDbExists}","LocalMediaDbExists":true,"SourceContext":"Umbraco.Web.PublishedCache.NuCache.PublishedSnapshotService","ProcessId":24260,"ProcessName":"iisexpress","ThreadId":15,"AppDomainId":3,"AppDomainAppId":"LMW3SVC2ROOT","MachineName":"AAR00112","Log4NetLevel":"INFO ","HttpRequestNumber":3,"HttpRequestId":"d54778bf-69dc-4f18-be69-5afa9cfa20b6"}
{"@t":"2022-02-10T07:48:14.3380829Z","@mt":"{StartMessage} [Timing {TimingId}]","StartMessage":"Loading content from local cache file","TimingId":"89630cc","SourceContext":"Umbraco.Web.PublishedCache.NuCache.PublishedSnapshotService","ProcessId":24260,"ProcessName":"iisexpress","ThreadId":15,"AppDomainId":3,"AppDomainAppId":"LMW3SVC2ROOT","MachineName":"AAR00112","Log4NetLevel":"INFO ","HttpRequestNumber":3,"HttpRequestId":"d54778bf-69dc-4f18-be69-5afa9cfa20b6"}
{"@t":"2022-02-10T07:48:14.3750825Z","@mt":"{EndMessage} ({Duration}ms) [Timing {TimingId}]","EndMessage":"Completed.","Duration":37,"TimingId":"89630cc","SourceContext":"Umbraco.Web.PublishedCache.NuCache.PublishedSnapshotService","ProcessId":24260,"ProcessName":"iisexpress","ThreadId":15,"AppDomainId":3,"AppDomainAppId":"LMW3SVC2ROOT","MachineName":"AAR00112","Log4NetLevel":"INFO ","HttpRequestNumber":3,"HttpRequestId":"d54778bf-69dc-4f18-be69-5afa9cfa20b6"}
{"@t":"2022-02-10T07:48:14.3870836Z","@mt":"{StartMessage} [Timing {TimingId}]","StartMessage":"Loading media from local cache file","TimingId":"bd2710d","SourceContext":"Umbraco.Web.PublishedCache.NuCache.PublishedSnapshotService","ProcessId":24260,"ProcessName":"iisexpress","ThreadId":15,"AppDomainId":3,"AppDomainAppId":"LMW3SVC2ROOT","MachineName":"AAR00112","Log4NetLevel":"INFO ","HttpRequestNumber":3,"HttpRequestId":"d54778bf-69dc-4f18-be69-5afa9cfa20b6"}
{"@t":"2022-02-10T07:48:14.3881044Z","@mt":"{EndMessage} ({Duration}ms) [Timing {TimingId}]","EndMessage":"Completed.","Duration":0,"TimingId":"bd2710d","SourceContext":"Umbraco.Web.PublishedCache.NuCache.PublishedSnapshotService","ProcessId":24260,"ProcessName":"iisexpress","ThreadId":15,"AppDomainId":3,"AppDomainAppId":"LMW3SVC2ROOT","MachineName":"AAR00112","Log4NetLevel":"INFO ","HttpRequestNumber":3,"HttpRequestId":"d54778bf-69dc-4f18-be69-5afa9cfa20b6"}
{"@t":"2022-02-10T07:48:33.6692732Z","@mt":"{LogPrefix} Canceling tasks","LogPrefix":"[RebuildIndexesOnStartup] ","SourceContext":"Umbraco.Web.Scheduling.BackgroundTaskRunner","ProcessId":24260,"ProcessName":"iisexpress","ThreadId":16,"AppDomainId":2,"AppDomainAppId":"LMW3SVC2ROOT","MachineName":"AAR00112","Log4NetLevel":"INFO "}
{"@t":"2022-02-10T07:48:33.7100962Z","@mt":"Application shutdown. Details: {ShutdownReason}\r\n\r\n_shutDownMessage={ShutdownMessage}\r\n\r\n_shutDownStack={ShutdownStack}","ShutdownReason":"ConfigurationChange","ShutdownMessage":"Change in App_Offline.htm\r\nHostingEnvironment initiated shutdown\r\nChange in App_Offline.htm\r\nChange in App_Offline.htm\r\nHostingEnvironment caused shutdown","ShutdownStack":"   at System.Environment.GetStackTrace(Exception e, Boolean needFileInfo)\r\n   at System.Environment.get_StackTrace()\r\n   at System.Web.Hosting.HostingEnvironment.InitiateShutdownInternal()\r\n   at System.Web.Hosting.HostingEnvironment.InitiateShutdownWithoutDemand()\r\n   at System.Web.HttpRuntime.ShutdownAppDomain(String stackTrace)\r\n   at System.Web.HttpRuntime.OnAppOfflineFileChange(Object sender, FileChangeEvent e)\r\n   at System.Web.DirectoryMonitor.FireNotifications()\r\n   at System.Web.Util.WorkItem.CallCallbackWithAssert(WorkItemCallback callback)\r\n   at System.Web.Util.WorkItem.OnQueueUserWorkItemCompletion(Object state)\r\n   at System.Threading.ExecutionContext.RunInternal(ExecutionContext executionContext, ContextCallback callback, Object state, Boolean preserveSyncCtx)\r\n   at System.Threading.ExecutionContext.Run(ExecutionContext executionContext, ContextCallback callback, Object state, Boolean preserveSyncCtx)\r\n   at System.Threading.QueueUserWorkItemCallback.System.Threading.IThreadPoolWorkItem.ExecuteWorkItem()\r\n   at System.Threading.ThreadPoolWorkQueue.Dispatch()","SourceContext":"Umbraco.Web.UmbracoApplicationBase","ProcessId":24260,"ProcessName":"iisexpress","ThreadId":5,"AppDomainId":2,"AppDomainAppId":"LMW3SVC2ROOT","MachineName":"AAR00112","Log4NetLevel":"INFO "}
